<?xml version="1.0" encoding="UTF-8"?>
<databaseChangeLog xmlns="http://www.liquibase.org/xml/ns/dbchangelog"
                   xmlns:xsi="http://www.w3.org/2001/XMLSchema-instance"
                   xsi:schemaLocation="http://www.liquibase.org/xml/ns/dbchangelog
                   https://www.liquibase.org/xml/ns/dbchangelog/dbchangelog-latest.xsd">

    <changeSet id="add-text-to-translate-column-to-bookmark-20240908-1900" author="suyeon">
        <addColumn tableName="bookmark">
            <column name="text_to_translate" type="varchar(255)"/>
        </addColumn>
    </changeSet>

    <changeSet id="add-title-to-translate-column-to-post-20240908-1900" author="suyeon">
        <addColumn tableName="post">
            <column name="title_to_translate" type="varchar(30)"/>
        </addColumn>
    </changeSet>

    <changeSet id="add-text-to-translate-column-to-post-20240908-1900" author="suyeon">
        <addColumn tableName="post">
            <column name="text_to_translate" type="varchar(255)"/>
        </addColumn>
    </changeSet>

    <changeSet id="add-text-to-translate-column-to-comment-20240908-1900" author="suyeon">
        <addColumn tableName="comment">
            <column name="text_to_comment" type="varchar(255)"/>
        </addColumn>
    </changeSet>

    <changeSet id="add-text-to-translate-column-to-chat-20240908-1900" author="suyeon">
        <addColumn tableName="chat">
            <column name="text_to_translate" type="varchar(255)"/>
        </addColumn>
    </changeSet>

</databaseChangeLog>